aemm/__init__.py
aemm/core/__init__.py
aemm/core/model.py
aemm/core/model_key.py
aemm/core/model_measure.py
aemm/core/model_type.py
aemm/core/rates/__init__.py
aemm/core/rates/autoregressive/__init__.py
aemm/core/rates/dual_measure/__init__.py
aemm/core/rates/forward_rate/__init__.py
aemm/core/rates/forward_rate/forward_rate_model.py
aemm/core/rates/short_rate/__init__.py
aemm/pretrained/__init__.py
aemm/pretrained/rates/__init__.py
aemm/stub/__init__.py
aemm/stub/rates/__init__.py
aemm-0.0.2.dist-info/LICENSE
aemm-0.0.2.dist-info/METADATA
aemm-0.0.2.dist-info/WHEEL
aemm-0.0.2.dist-info/top_level.txt
aemm-0.0.2.dist-info/RECORD
