Metadata-Version: 2.1
Name: aemm
Version: 0.0.2
Summary: Autoencoder Market Models (AEMM)
Home-page: https://github.com/compatibl/aemm
Author: The Project Contributors
License: UNKNOWN
Project-URL: Source Code, https://github.com/compatibl/aemm
Platform: UNKNOWN
Classifier: Development Status :: 3 - Alpha
Classifier: Intended Audience :: Developers
Classifier: Intended Audience :: Science/Research
Classifier: Intended Audience :: Financial and Insurance Industry
Classifier: Topic :: Software Development
Classifier: Topic :: Scientific/Engineering
Classifier: License :: OSI Approved :: Apache Software License
Classifier: Programming Language :: Python :: 3.9
Classifier: Programming Language :: Python :: 3.10
Classifier: Programming Language :: Python :: 3.11
Classifier: Operating System :: OS Independent
License-File: LICENSE
Requires-Dist: aenc (>=0.0.1)
Requires-Dist: cl-runtime (>=2.0.0)
Requires-Dist: numpy (>=1.17.4)
Requires-Dist: pandas (>=0.25.3)
Requires-Dist: pdoc (>=12.0.2)
Requires-Dist: plotly (>=4.14.3)
Requires-Dist: pytest (>=6.1.1)
Requires-Dist: scikit-learn (==1.0.1)
Requires-Dist: torch (>=1.12.1)
